{"difficulty": "notRanked", "id": 8, "handholds": {"hold8": {"width": 0.3892857142857143, "positionX": 18.413169642857145, "positionY": 4.381919642857142, "restitution": 1, "friction": 1, "gripTexture": "canyon/handholdgrabbed.png", "glowTexture": "canyon/handholdglow.png", "crumble": False, "texture": "canyon/handhold.png", "height": 0.3892857142857143}, "hold9": {"width": 0.3892857142857143, "positionX": 15.663169642857147, "positionY": 6.7256696428571425, "restitution": 1, "friction": 1, "gripTexture": "canyon/handholdgrabbed.png", "glowTexture": "canyon/handholdglow.png", "crumble": False, "texture": "canyon/handhold.png", "height": 0.3892857142857143}, "hold0": {"width": 0.5, "positionX": 6.21875, "positionY": 9.90625, "restitution": 1, "friction": 1, "gripTexture": "canyon/handholdgrabbed.png", "glowTexture": "canyon/handholdglow.png", "crumble": False, "texture": "canyon/handhold.png", "height": 0.5}, "hold1": {"width": 0.5, "positionX": 17.15625, "positionY": 9.96875, "restitution": 1, "friction": 1, "gripTexture": "canyon/handholdgrabbed.png", "glowTexture": "canyon/handholdglow.png", "crumble": False, "texture": "canyon/handhold.png", "height": 0.5}, "hold2": {"width": 0.5, "positionX": 13.84375, "positionY": 8.375, "restitution": 1, "friction": 1, "gripTexture": "canyon/handholdgrabbed.png", "glowTexture": "canyon/handholdglow.png", "crumble": False, "texture": "canyon/handhold.png", "height": 0.5}, "hold3": {"width": 0.5, "positionX": 19.84375, "positionY": 8.5625, "restitution": 1, "friction": 1, "gripTexture": "canyon/handholdgrabbed.png", "glowTexture": "canyon/handholdglow.png", "crumble": False, "texture": "canyon/handhold.png", "height": 0.5}, "hold4": {"width": 0.5, "positionX": 12.03125, "positionY": 5.687500000000001, "restitution": 1, "friction": 1, "gripTexture": "canyon/handholdgrabbed.png", "glowTexture": "canyon/handholdglow.png", "crumble": False, "texture": "canyon/handhold.png", "height": 0.5}, "hold5": {"width": 0.5, "positionX": 22.75, "positionY": 11.406250000000002, "restitution": 1, "friction": 1, "gripTexture": "canyon/handholdgrabbed.png", "glowTexture": "canyon/handholdglow.png", "crumble": False, "texture": "canyon/handhold.png", "height": 0.5}, "hold6": {"width": 0.5, "positionX": 20.75, "positionY": 4.062500000000001, "restitution": 1, "friction": 1, "gripTexture": "canyon/handholdgrabbed.png", "glowTexture": "canyon/handholdglow.png", "crumble": False, "texture": "canyon/handhold.png", "height": 0.5}, "hold7": {"width": 0.3892857142857143, "positionX": 16.22566964285714, "positionY": 3.1631696428571425, "restitution": 1, "friction": 1, "gripTexture": "canyon/handholdgrabbed.png", "glowTexture": "canyon/handholdglow.png", "crumble": False, "texture": "canyon/handhold.png", "height": 0.3892857142857143}, "hold12": {"width": 0.3892857142857143, "positionX": 21.069419642857145, "positionY": 14.006919642857142, "restitution": 1, "friction": 1, "gripTexture": "canyon/handholdgrabbed.png", "glowTexture": "canyon/handholdglow.png", "crumble": False, "texture": "canyon/handhold.png", "height": 0.3892857142857143}, "hold13": {"width": 0.3892857142857143, "positionX": 15.819419642857143, "positionY": 15.413169642857143, "restitution": 1, "friction": 1, "gripTexture": "canyon/handholdgrabbed.png", "glowTexture": "canyon/handholdglow.png", "crumble": False, "texture": "canyon/handhold.png", "height": 0.3892857142857143}, "hold10": {"width": 0.3892857142857143, "positionX": 14.569419642857143, "positionY": 12.256919642857143, "restitution": 1, "friction": 1, "gripTexture": "canyon/handholdgrabbed.png", "glowTexture": "canyon/handholdglow.png", "crumble": False, "texture": "canyon/handhold.png", "height": 0.3892857142857143}, "hold11": {"width": 0.3892857142857143, "positionX": 11.600669642857143, "positionY": 11.569419642857143, "restitution": 1, "friction": 1, "gripTexture": "canyon/handholdgrabbed.png", "glowTexture": "canyon/handholdglow.png", "crumble": False, "texture": "canyon/handhold.png", "height": 0.3892857142857143}, "hold16": {"width": 0.3892857142857143, "positionX": 26.13191964285714, "positionY": 17.38191964285714, "restitution": 1, "friction": 1, "gripTexture": "canyon/handholdgrabbed.png", "glowTexture": "canyon/handholdglow.png", "crumble": False, "texture": "canyon/handhold.png", "height": 0.3892857142857143}, "hold17": {"width": 0.3892857142857143, "positionX": 20.47566964285714, "positionY": 17.50691964285714, "restitution": 1, "friction": 1, "gripTexture": "canyon/handholdgrabbed.png", "glowTexture": "canyon/handholdglow.png", "crumble": False, "texture": "canyon/handhold.png", "height": 0.3892857142857143}, "hold14": {"width": 0.3892857142857143, "positionX": 10.444419642857143, "positionY": 15.881919642857145, "restitution": 1, "friction": 1, "gripTexture": "canyon/handholdgrabbed.png", "glowTexture": "canyon/handholdglow.png", "crumble": False, "texture": "canyon/handhold.png", "height": 0.3892857142857143}, "hold15": {"width": 0.3892857142857143, "positionX": 21.63191964285714, "positionY": 18.91316964285714, "restitution": 1, "friction": 1, "gripTexture": "canyon/handholdgrabbed.png", "glowTexture": "canyon/handholdglow.png", "crumble": False, "texture": "canyon/handhold.png", "height": 0.3892857142857143}, "hold18": {"width": 0.3892857142857143, "positionX": 14.256919642857143, "positionY": 19.91316964285714, "restitution": 1, "friction": 1, "gripTexture": "canyon/handholdgrabbed.png", "glowTexture": "canyon/handholdglow.png", "crumble": False, "texture": "canyon/handhold.png", "height": 0.3892857142857143}}, "size": 20}